{"authors": ["Christine Hauser", "Jesus Jiménez", "Livia Albeck-Ripka"], "date_download": "2023-03-28 16:43:58", "date_modify": "2023-03-28 16:43:58", "date_publish": "2023-03-23 14:43:25", "description": "Several hostages were rescued during a multiday operation involving multiple law enforcement agencies, the F.B.I. said. One suspect died after “an agent-involved shooting” and a second was taken into custody.", "filename": "2023_03_23_us_houston-hostages-fbi_1680021838.html", "image_url": "https://static01.nyt.com/images/2023/03/23/multimedia/23xp-houston-pcgl/23xp-houston-pcgl-facebookJumbo.jpg", "language": "en", "localpath": "/home/mwaldrich/news-please-repo//data/2023/03/28/nytimes.com/2023_03_23_us_houston-hostages-fbi_1680021838.html", "title": "Suspect Dead After Hostages Rescued in Houston F.B.I. Operation", "title_page": "Suspect Dead After Hostages Rescued in Houston F.B.I. Operation - The New York Times", "title_rss": "NULL", "source_domain": "nytimes.com", "maintext": "A hostage rescue in Houston that lasted several days ended on Thursday with one suspect shot dead and a second suspect in custody, the F.B.I. said.\nThe federal agency had been working to rescue two hostages held in a Studio 6 motel in the Houston area when the shooting happened at about 4:30 a.m., officials said at a news conference on Thursday.\nJames Smith, the special agent in charge of the F.B.I.’s Houston office, said that the two hostages had been “safely rescued,” and that the second suspect had been detained by the Harris County Sheriff’s Department. “No agents were injured,” he added. “At this time, there is no threat to public safety.”\nA prosecutor told The Associated Press on Thursday that the situation began days ago when three migrants were kidnapped from a vehicle in a neighboring county.", "url": "https://www.nytimes.com/2023/03/23/us/houston-hostages-fbi.html"}