{"authors": ["The Learning Network"], "date_download": "2023-03-28 17:30:11", "date_modify": "2023-03-28 17:30:11", "date_publish": "2023-03-16 07:00:02", "description": "Tell us a story, real or made up, about an activity you enjoyed as a child that you gave up as you got older.", "filename": "2023_03_16_learning_childhood-hobbies_1680024611.html", "image_url": "https://static01.nyt.com/images/2023/03/04/multimedia/04-THE-MORNING-NL/04-THE-MORNING-NL-facebookJumbo.jpg", "language": "en", "localpath": "/home/mwaldrich/news-please-repo//data/2023/03/28/nytimes.com/2023_03_16_learning_childhood-hobbies_1680024611.html", "title": "Childhood Hobbies", "title_page": "Childhood Hobbies - The New York Times", "title_rss": "NULL", "source_domain": "nytimes.com", "maintext": "Describe a memory of a hobby or activity you used to enjoy as a child that you no longer participate in — whether because you feel you’ve aged out of it, because you don’t have time, or for any other reason. Do your best to make your memory vivid, so that readers understand why this activity gave you joy.\nPost your memory in the comments, then read the related article to learn about Times readers who have rediscovered childhood hobbies.\nStudents 13 and older in the United States and Britain, and 16 and older elsewhere, are invited to comment. All comments are moderated by the Learning Network staff, but please keep in mind that once your comment is accepted, it will be made public and may appear in print.\nFind more Picture Prompts here.", "url": "https://www.nytimes.com/2023/03/16/learning/childhood-hobbies.html"}